<?xml version="1.0" encoding="UTF-8"?>
<persistence xmlns="http://xmlns.jcp.org/xml/ns/persistence" version="2.1">
    <persistence-unit name="dev" transaction-type="RESOURCE_LOCAL">

        <description>
            Persistence Unit for io Bank production environment.
        </description>

        <provider>org.hibernate.jpa.HibernatePersistenceProvider</provider>
        <properties>
            <property name="jakarta.persistence.jdbc.driver" value="org.postgresql.Driver"/>
            <property name="jakarta.persistence.jdbc.url" value="jdbc:postgresql://localhost:5432/ioBank?useSSL=false"/>
            <property name="jakarta.persistence.jdbc.user" value="miguel"/>
            <property name="jakarta.persistence.jdbc.password" value=""/>
            <property name="hibernate.dialect" value="org.hibernate.dialect.PostgreSQL95Dialect"/>
            <property name="hibernate.format_sql" value="true"/>
            <property name="hibernate.hbm2ddl.auto" value="create"/>
            <property name="hibernate.hbm2ddl.import_files" value="db/db.sql"/>
            <property name="hibernate.hbm2ddl.import_files_sql_extractor" value="org.hibernate.tool.hbm2ddl.MultipleLinesSqlCommandExtractor"/>
        </properties>
    </persistence-unit>
</persistence>

